nodeenv.py
nodeenv-1.7.0.dist-info/AUTHORS
nodeenv-1.7.0.dist-info/LICENSE
nodeenv-1.7.0.dist-info/METADATA
nodeenv-1.7.0.dist-info/WHEEL
nodeenv-1.7.0.dist-info/entry_points.txt
nodeenv-1.7.0.dist-info/top_level.txt
nodeenv-1.7.0.dist-info/RECORD
